peerdid/__init__.py
peerdid/dids.py
peerdid/errors.py
peerdid/keys.py
peerdid/core/__init__.py
peerdid/core/jwk_okp.py
peerdid/core/multibase.py
peerdid/core/multicodec.py
peerdid/core/peer_did_helper.py
peerdid/core/utils.py
peerdid-0.5.2.dist-info/LICENSE
peerdid-0.5.2.dist-info/METADATA
peerdid-0.5.2.dist-info/WHEEL
peerdid-0.5.2.dist-info/top_level.txt
peerdid-0.5.2.dist-info/RECORD
