Metadata-Version: 2.1
Name: peerdid
Version: 0.5.2
Summary: PeerDID for Python
Home-page: https://github.com/sicpa-dlab/peer-did-python
Author: SICPA
Author-email: DLCHOpenSourceContrib@sicpa.com
License: Apache-2.0
Project-URL: Source Code, https://github.com/sicpa-dlab/peer-did-python
Project-URL: Issue Tracker, https://github.com/sicpa-dlab/peer-did-python/issues/
Classifier: License :: OSI Approved :: Apache Software License
Classifier: Operating System :: OS Independent
Classifier: Programming Language :: Python
Classifier: Programming Language :: Python :: 3
Classifier: Programming Language :: Python :: 3.7
Classifier: Programming Language :: Python :: 3.8
Classifier: Programming Language :: Python :: 3.9
Classifier: Programming Language :: Python :: 3.10
Requires-Python: >=3.7
License-File: LICENSE
Requires-Dist: base58 (~=2.1.0)
Requires-Dist: pydid (~=0.3.5)
Requires-Dist: varint (~=1.0.2)
Provides-Extra: tests
Requires-Dist: pytest (==6.2.5) ; extra == 'tests'
Requires-Dist: pytest-xdist (==2.3.0) ; extra == 'tests'
